dataspecs/__init__.py
dataspecs/py.typed
dataspecs/core/__init__.py
dataspecs/core/api.py
dataspecs/core/specs.py
dataspecs/core/typing.py
dataspecs/extras/__init__.py
dataspecs/extras/formatting.py
dataspecs/extras/naming.py
dataspecs/extras/replacing.py
dataspecs-5.0.0.dist-info/METADATA
dataspecs-5.0.0.dist-info/WHEEL
dataspecs-5.0.0.dist-info/licenses/LICENSE
dataspecs-5.0.0.dist-info/RECORD
