Metadata-Version: 2.4
Name: dataspecs
Version: 5.0.0
Summary: Data specifications by data classes
Project-URL: homepage, https://astropenguin.github.io/dataspecs/v5.0.0
Project-URL: repository, https://github.com/astropenguin/dataspecs
Author-email: Akio Taniguchi <taniguchi.akio@gmail.com>
License: MIT License
License-File: LICENSE
Keywords: dataclasses,specifications,typing
Classifier: License :: OSI Approved :: MIT License
Classifier: Programming Language :: Python :: 3
Classifier: Programming Language :: Python :: 3.9
Classifier: Programming Language :: Python :: 3.10
Classifier: Programming Language :: Python :: 3.11
Classifier: Programming Language :: Python :: 3.12
Classifier: Programming Language :: Python :: 3.13
Requires-Python: <3.14,>=3.9
Requires-Dist: typing-extensions<5.0,>=4.1
